vanna/__init__.py
vanna/local.py
vanna/remote.py
vanna/utils.py
vanna/ZhipuAI/ZhipuAI_Chat.py
vanna/ZhipuAI/ZhipuAI_embeddings.py
vanna/ZhipuAI/__init__.py
vanna/advanced/__init__.py
vanna/anthropic/__init__.py
vanna/anthropic/anthropic_chat.py
vanna/base/__init__.py
vanna/base/base.py
vanna/chromadb/__init__.py
vanna/chromadb/chromadb_vector.py
vanna/exceptions/__init__.py
vanna/flask/__init__.py
vanna/flask/assets.py
vanna/flask/auth.py
vanna/google/__init__.py
vanna/google/gemini_chat.py
vanna/hf/__init__.py
vanna/hf/hf.py
vanna/marqo/__init__.py
vanna/marqo/marqo.py
vanna/milvus/__init__.py
vanna/milvus/milvus_vector.py
vanna/mistral/__init__.py
vanna/mistral/mistral.py
vanna/mock/__init__.py
vanna/mock/embedding.py
vanna/mock/llm.py
vanna/mock/vectordb.py
vanna/ollama/__init__.py
vanna/ollama/ollama.py
vanna/openai/__init__.py
vanna/openai/openai_chat.py
vanna/openai/openai_embeddings.py
vanna/opensearch/__init__.py
vanna/opensearch/opensearch_vector.py
vanna/pgvectorestore/__init__.py
vanna/pgvectorestore/pgvectore.py
vanna/pinecone/__init__.py
vanna/pinecone/pinecone_vector.py
vanna/qdrant/__init__.py
vanna/qdrant/qdrant.py
vanna/types/__init__.py
vanna/vannadb/__init__.py
vanna/vannadb/vannadb_vector.py
vanna/vllm/__init__.py
vanna/vllm/vllm.py
vanna_edited-0.1.0.dist-info/METADATA
vanna_edited-0.1.0.dist-info/WHEEL
vanna_edited-0.1.0.dist-info/top_level.txt
vanna_edited-0.1.0.dist-info/RECORD
